diamondonpy/__init__.py
diamondonpy/__main__.py
diamondonpy/diamond.py
diamondonpy/errors.py
tests/__init__.py
tests/conftest.py
tests/test_diamond.py
tests/test_integration.py
tests/test_main.py
diamondonpy-0.1.1.dist-info/LICENSE
diamondonpy-0.1.1.dist-info/METADATA
diamondonpy-0.1.1.dist-info/WHEEL
diamondonpy-0.1.1.dist-info/entry_points.txt
diamondonpy-0.1.1.dist-info/top_level.txt
diamondonpy-0.1.1.dist-info/RECORD
