Metadata-Version: 2.2
Name: diamondonpy
Version: 0.1.1
Summary: A Python wrapper for the DIAMOND bioinformatics tool
Author: Enzo Guerrero-Araya
Requires-Python: >=3.6
License-File: LICENSE
Requires-Dist: pandas>=1.0.0
Requires-Dist: numpy>=1.18.0
Provides-Extra: dev
Requires-Dist: pytest>=6.0; extra == "dev"
Requires-Dist: pytest-cov>=2.0; extra == "dev"
Requires-Dist: pytest-mock>=3.0; extra == "dev"
Dynamic: author
Dynamic: requires-python
